Pydule.py
Pydule-3.4.1.dist-info/METADATA
Pydule-3.4.1.dist-info/WHEEL
Pydule-3.4.1.dist-info/top_level.txt
Pydule-3.4.1.dist-info/RECORD
