Metadata-Version: 2.1
Name: Pydule
Version: 3.4.1
Summary: Access ChatGPT, Remove Background, AI Generated Image, Track Location, Play Songs, Create Qrcode, Copy Text, Translate a Sentence to Other Language and more..
Author: D.Tamil Mutharasan
Keywords: python,PyDule,Module,Pydule,pydule,matrix,qrcode,youtube,weather,list,tuple,set,dictionary,clear,color,pick_color,open,app,search,play,mp3,song,restart,system,shutdown,date,time,text_to_speech,text,speech
Classifier: Programming Language :: Python :: 3
Classifier: License :: OSI Approved :: MIT License
Classifier: Intended Audience :: Education
Classifier: Operating System :: Microsoft :: Windows :: Windows 10
Classifier: Development Status :: 5 - Production/Stable
Requires-Python: >=3.10.7
Requires-Dist: beautifulsoup4
Requires-Dist: pyttsx3
Requires-Dist: pywhatkit
Requires-Dist: pyglet
Requires-Dist: datetime
Requires-Dist: requests
Requires-Dist: psutil
Requires-Dist: AppOpener
Requires-Dist: deep-translator
Requires-Dist: qrcode
Requires-Dist: numpy
Requires-Dist: pyperclip
Requires-Dist: soundfile
Requires-Dist: soundcard
Requires-Dist: pyautogui
Requires-Dist: pyaudio
Requires-Dist: wave
Requires-Dist: opencv-python
Requires-Dist: openai
Requires-Dist: phonenumbers
Requires-Dist: SpeechRecognition
Requires-Dist: Pillow
Requires-Dist: pyinstaller
Requires-Dist: pyfiglet
Requires-Dist: pygame
Requires-Dist: speedtest-cli
Requires-Dist: keyboard
Requires-Dist: moviepy
Requires-Dist: demoji
Requires-Dist: win10toast
